Metadata-Version: 2.1
Name: s1_store
Version: 0.0.1
Summary: A package used to support the image storage and has the upload, retreive , Delete and update function
Author: CIA LABS
License-File: LICENSE
